<?xml version="1.0" encoding="UTF-8"?>
<java version="1.8.0_40" class="java.beans.XMLDecoder">
 <object class="java.util.ArrayList">
  <void method="add">
   <string>Ball</string>
  </void>
  <void method="add">
   <string>Ball &amp; Paddle</string>
  </void>
  <void method="add">
   <string>Casino</string>
  </void>
  <void method="add">
   <string>Casino * Mature *</string>
  </void>
  <void method="add">
   <string>Climbing</string>
  </void>
  <void method="add">
   <string>Driving</string>
  </void>
  <void method="add">
   <string>Electromechanical</string>
  </void>
  <void method="add">
   <string>Fighter</string>
  </void>
  <void method="add">
   <string>Maze</string>
  </void>
  <void method="add">
   <string>Maze * Mature *</string>
  </void>
  <void method="add">
   <string>Misc.</string>
  </void>
  <void method="add">
   <string>Misc. * Mature *</string>
  </void>
  <void method="add">
   <string>Multi-cart Board</string>
  </void>
  <void method="add">
   <string>Multiplay</string>
  </void>
  <void method="add">
       <string>Not Classified</string>
    </void>
  <void method="add">
   <string>Pinball</string>
  </void>
  <void method="add">
   <string>Pinball * Mature *</string>
  </void>
  <void method="add">
   <string>Platform</string>
  </void>
  <void method="add">
   <string>Puzzle</string>
  </void>
  <void method="add">
   <string>Quiz</string>
  </void>
  <void method="add">
   <string>Rhythm</string>
  </void>
  <void method="add">
   <string>Shooter</string>
  </void>
  <void method="add">
   <string>Sports</string>
  </void>
  <void method="add">
   <string>System</string>
  </void>
  <void method="add">
   <string>Tabletop</string>
  </void>
  <void method="add">
   <string>Utilities</string>
  </void>
 </object>
</java>
